{"name":"other","slug":"other","count":2,"postlist":[{"title":"66、Mac系统升级后桌面文件夹及文件消失","uid":"7b7501b7603f5fa7dd1b27a67cca3065","slug":"66-mac-finder","date":"2022-04-19T15:30:00.000Z","updated":"2022-09-05T08:00:05.000Z","comments":true,"path":"api/articles/66-mac-finder.json","keywords":null,"cover":null,"text":"解决方式：终端输入如下命令即可 shelldefaults write com.apple.finder CreateDesktop -bool true; k...","permalink":"/post/66-mac-finder","photos":[],"count_time":{"symbolsCount":126,"symbolsTime":"1 mins."},"categories":[],"tags":[{"name":"other","slug":"other","count":2,"path":"api/tags/other.json"}],"author":{"name":"Jude","slug":"blog-author","avatar":"","link":"/","description":"","socials":{"github":"","twitter":"","stackoverflow":"","wechat":"","qq":"","weibo":"","zhihu":"","csdn":"","juejin":"","customs":{}}}},{"title":"60、什么是上位机、下位机?","uid":"078fde9ad4b31fe5df06fa312dcb9f33","slug":"60-Upper-Lower","date":"2022-02-28T12:00:00.000Z","updated":"2022-09-05T07:58:23.000Z","comments":true,"path":"api/articles/60-Upper-Lower.json","keywords":null,"cover":null,"text":"上位机在系统中起主控作用，主要作为系统的规划控制，属于决策层；而下位机是具体执行层，主要完成系统规划层下达的任务。 1.通常上位机和下位机通讯可以采用不同的通讯...","permalink":"/post/60-Upper-Lower","photos":[],"count_time":{"symbolsCount":397,"symbolsTime":"1 mins."},"categories":[],"tags":[{"name":"other","slug":"other","count":2,"path":"api/tags/other.json"}],"author":{"name":"Jude","slug":"blog-author","avatar":"","link":"/","description":"","socials":{"github":"","twitter":"","stackoverflow":"","wechat":"","qq":"","weibo":"","zhihu":"","csdn":"","juejin":"","customs":{}}}}]}